{"height": 256, "width": 256, "file_index": 7041, "nr_part": 1, "dataset": "ade20k"}
{"height": 375, "width": 500, "file_index": 9765, "nr_part": 1, "dataset": "pascal"}
{"height": 512, "width": 683, "file_index": 4509, "nr_part": 0, "dataset": "ade20k"}
{"height": 310, "width": 450, "file_index": 2389, "nr_part": 1, "dataset": "ade20k"}
{"height": 512, "width": 768, "file_index": 8486, "nr_part": 1, "dataset": "ade20k"}
{"height": 512, "width": 683, "file_index": 2579, "nr_part": 1, "dataset": "ade20k"}
{"height": 375, "width": 500, "file_index": 1456, "nr_part": 1, "dataset": "pascal"}
{"height": 256, "width": 256, "file_index": 9294, "nr_part": 0, "dataset": "ade20k"}
